url_converter/__init__.py
url_converter-0.0.0.dev1.dist-info/LICENSE
url_converter-0.0.0.dev1.dist-info/METADATA
url_converter-0.0.0.dev1.dist-info/WHEEL
url_converter-0.0.0.dev1.dist-info/top_level.txt
url_converter-0.0.0.dev1.dist-info/RECORD
